{
  "name": "@redux-model/react-native",
  "version": "6.8.3",
  "keywords": [
    "react",
    "redux-model",
    "redux",
    "model",
    "typescript",
    "react-native"
  ],
  "main": "libs/index.js",
  "types": "libs/index.d.ts",
  "repository": "https://github.com/redux-model/redux-model",
  "author": "范文华 <531362022@qq.com>",
  "license": "MIT",
  "peerDependencies": {
    "react-redux": "*"
  },
  "dependencies": {
    "axios": "^0.19.2",
    "immer": "^5.3.6",
    "lodash.clonedeep": "^4.5.0",
    "object-assign": "^4.1.1",
    "redux": "^4.0.5",
    "tslib": "^1.11.1"
  }
}
